<?xml version="1.0" encoding="UTF-8" ?><!DOCTYPE mapper PUBLIC "-//mybatis.org//DTD Mapper 3.0//EN" "http://mybatis.org/dtd/mybatis-3-mapper.dtd" ><mapper namespace="com.zhilai.master.modules.notice.dao.CorpNoticeTemplateDao" >	<resultMap type="com.zhilai.master.modules.notice.entity.CorpNoticeTemplate" id="corpNoticeTemplateMap">		<result property="logid" column="logid" />		<result property="corptemp_id" column="corptemp_id" />		<result property="corp_id" column="corp_id" />		<result property="corp_name" column="corp_name" />		<result property="temp_id" column="temp_id" />		<result property="temp_name" column="temp_name" />		<result property="main_type" column="main_type" />		<result property="sub_type" column="sub_type" />		<result property="notice_type" column="notice_type" />		<result property="role_id" column="role_id" />		<result property="role_name" column="role_name" />		<result property="send_num" column="send_num" />		<result property="cur_state" column="cur_state" />		<result property="interval_time" column="interval_time" />		<result property="content" column="content" />		<result property="description" column="description" />		<result property="level" column="level" />		<result property="create_time" column="create_time" />	</resultMap>		<sql id="Base_Column_List">		logid, corptemp_id, corp_id, corp_name, temp_id, 		temp_name, main_type, sub_type, notice_type, role_id, 		role_name, send_num, cur_state, interval_time, content, 		description, level, create_time	</sql>		<select id="findList" resultMap="corpNoticeTemplateMap">		SELECT <include refid="Base_Column_List" /> FROM as_corp_notice_template WHERE 1=1		<if test="temp_name != null and temp_name != ''">			AND (temp_name = #{temp_name} OR temp_name LIKE 					<if test="dbName == 'oracle'">'%'||#{temp_name}||'%')</if>					<if test="dbName == 'mssql'">'%'+#{temp_name}+'%')</if>					<if test="dbName == 'mysql'">CONCAT('%', #{temp_name}, '%'))</if>		</if>		<if test="content != null and content != ''">			AND (content = #{content} OR content LIKE 					<if test="dbName == 'oracle'">'%'||#{content}||'%')</if>					<if test="dbName == 'mssql'">'%'+#{content}+'%')</if>					<if test="dbName == 'mysql'">CONCAT('%', #{content}, '%'))</if>		</if>		<if test="main_type != null and main_type != ''">			AND main_type = #{main_type}		</if>		ORDER BY level,create_time DESC	</select>		<select id="findListByfileCode" resultMap="corpNoticeTemplateMap">		SELECT <include refid="Base_Column_List" /> 		FROM as_corp_notice_template		WHERE(content = #{fieldCode} OR content LIKE CONCAT('%', #{fieldCode}, '%'))	</select>		<select id="get" resultMap="corpNoticeTemplateMap">		SELECT <include refid="Base_Column_List" /> 		FROM as_corp_notice_template		WHERE logid = #{logid}	</select>		<select id="findAllNormal" resultMap="corpNoticeTemplateMap">		SELECT * FROM as_corp_notice_template WHERE cur_state = '0'	</select>		<delete id="delete">		DELETE FROM as_corp_notice_template		WHERE logid = #{logid}	</delete>		<insert id="insert">		INSERT INTO as_corp_notice_template(			logid, corptemp_id, corp_id, corp_name, temp_id,			temp_name, main_type, sub_type, notice_type, role_id,			role_name, send_num, cur_state, interval_time, content,			description, level, create_time )		VALUES(			#{logid}, #{corptemp_id}, #{corp_id}, #{corp_name}, #{temp_id},			#{temp_name}, #{main_type}, #{sub_type}, #{notice_type}, #{role_id},			#{role_name}, #{send_num}, #{cur_state}, #{interval_time}, #{content},			#{description}, #{level}, #{create_time} )	</insert>		<update id="update">		UPDATE as_corp_notice_template SET 			logid = #{logid},			corptemp_id = #{corptemp_id},			corp_id = #{corp_id},			corp_name = #{corp_name},			temp_id = #{temp_id},			temp_name = #{temp_name},			main_type = #{main_type},			sub_type = #{sub_type},			notice_type = #{notice_type},			role_id = #{role_id},			role_name = #{role_name},			send_num = #{send_num},			cur_state = #{cur_state},			interval_time = #{interval_time},			content = #{content},			description = #{description},			level = #{level},			create_time = #{create_time}		WHERE logid = #{logid}	</update></mapper>