<?xml version="1.0" encoding="UTF-8" ?><!DOCTYPE mapper PUBLIC "-//mybatis.org//DTD Mapper 3.0//EN" "http://mybatis.org/dtd/mybatis-3-mapper.dtd" ><mapper namespace="com.zhilai.master.modules.inventory.dao.CheckPlanDao" >		<sql id="Base_Column_List">		logid, plan_id, corp_id, corp_name, plan_type, 		target_id, target_name, cycle_type, cycle_value, check_type, 		check_obj, cur_state, state_time, create_time	</sql>		<select id="findList" resultType="CheckPlan">		SELECT <include refid="Base_Column_List" /> FROM as_check_plan WHERE 1=1		<if test="planType != null and planType != ''">			AND plan_type = #{planType} 		</if>		<if test="targetId != null and targetId != ''">			AND target_id = #{targetId}		</if>		<if test="cycleType != null and cycleType != ''">			AND cycle_type = #{cycleType}		</if>		<if test="curState != null and curState != ''">			AND cur_state = #{curState}		</if>		ORDER BY create_time DESC 	</select>		<select id="get" resultType="CheckPlan">		SELECT <include refid="Base_Column_List" /> 		FROM as_check_plan		WHERE plan_id = #{planId}	</select>		<delete id="delete">		DELETE FROM as_check_plan		WHERE plan_id = #{planId}	</delete>		<insert id="insert">		INSERT INTO as_check_plan(			logid, plan_id, corp_id, corp_name, plan_type,			target_id, target_name, cycle_type, cycle_value, check_type,			check_obj, cur_state, state_time, create_time )		VALUES(			#{logid}, #{planId}, #{corpId}, #{corpName}, #{planType},			#{targetId}, #{targetName}, #{cycleType}, #{cycleValue}, #{checkType},			#{checkObj}, #{curState}, #{stateTime}, #{createTime} )	</insert>		<update id="update">		UPDATE as_check_plan SET 			logid = #{logid},			plan_id = #{planId},			corp_id = #{corpId},			corp_name = #{corpName},			plan_type = #{planType},			target_id = #{targetId},			target_name = #{targetName},			cycle_type = #{cycleType},			cycle_value = #{cycleValue},			check_type = #{checkType},			check_obj = #{checkObj},			cur_state = #{curState},			state_time = #{stateTime},			create_time = #{createTime}		WHERE plan_id = #{planId}	</update></mapper>